getjson/__init__.py
getjson/requests_implementation.py
getjson-2.0.0.dist-info/METADATA
getjson-2.0.0.dist-info/WHEEL
getjson-2.0.0.dist-info/entry_points.txt
getjson-2.0.0.dist-info/top_level.txt
getjson-2.0.0.dist-info/RECORD
