Metadata-Version: 2.1
Name: getjson
Version: 2.0.0
Summary: Request JSON data en masse with backoff and failover
Home-page: https://github.com/microprediction/getjson
Author: microprediction
Author-email: info@microprediction.org
License: MIT
Platform: UNKNOWN
Classifier: License :: OSI Approved :: MIT License
Classifier: Programming Language :: Python :: 3
Classifier: Programming Language :: Python :: 3.7
Requires-Dist: backoff
Requires-Dist: requests
